mcpomni_connect/__init__.py
mcpomni_connect/cli.py
mcpomni_connect/client.py
mcpomni_connect/constants.py
mcpomni_connect/llm.py
mcpomni_connect/llm_support.py
mcpomni_connect/main.py
mcpomni_connect/notifications.py
mcpomni_connect/prompts.py
mcpomni_connect/refresh_server_capabilities.py
mcpomni_connect/resources.py
mcpomni_connect/sampling.py
mcpomni_connect/system_prompts.py
mcpomni_connect/tools.py
mcpomni_connect/types.py
mcpomni_connect/utils.py
mcpomni_connect/agents/__init__.py
mcpomni_connect/agents/base.py
mcpomni_connect/agents/orchestrator.py
mcpomni_connect/agents/react_agent.py
mcpomni_connect/agents/sequential_agents.py
mcpomni_connect/agents/token_usage.py
mcpomni_connect/agents/tool_calling_agent.py
mcpomni_connect/agents/types.py
mcpomni_connect/agents/tools/__init__.py
mcpomni_connect/agents/tools/local_tools_registry.py
mcpomni_connect/agents/tools/tools_handler.py
mcpomni_connect/database/__init__.py
mcpomni_connect/database/database_message_store.py
mcpomni_connect/events/__init__.py
mcpomni_connect/events/base.py
mcpomni_connect/events/event_router.py
mcpomni_connect/events/in_memory.py
mcpomni_connect/events/redis_stream.py
mcpomni_connect/memory_store/__init__.py
mcpomni_connect/memory_store/base.py
mcpomni_connect/memory_store/database_memory.py
mcpomni_connect/memory_store/in_memory.py
mcpomni_connect/memory_store/memory_router.py
mcpomni_connect/memory_store/redis_memory.py
mcpomni_connect/memory_store/memory_management/__init__.py
mcpomni_connect/memory_store/memory_management/chromadb_vector_db.py
mcpomni_connect/memory_store/memory_management/memory_manager.py
mcpomni_connect/memory_store/memory_management/qdrant_vector_db.py
mcpomni_connect/memory_store/memory_management/shared_embedding.py
mcpomni_connect/memory_store/memory_management/system_prompts.py
mcpomni_connect/memory_store/memory_management/vector_db_base.py
mcpomni_connect/omni_agent/__init__.py
mcpomni_connect/omni_agent/agent.py
mcpomni_connect-0.1.22.dist-info/METADATA
mcpomni_connect-0.1.22.dist-info/WHEEL
mcpomni_connect-0.1.22.dist-info/entry_points.txt
mcpomni_connect-0.1.22.dist-info/licenses/LICENSE
mcpomni_connect-0.1.22.dist-info/RECORD
