Metadata-Version: 2.4
Name: mcpomni_connect
Version: 0.1.22
Summary: Universal MCP Client with multi-transport support and LLM-powered tool routing
Project-URL: Repository, https://github.com/Abiorh001/mcp_omni_connect
Project-URL: Issues, https://github.com/Abiorh001/mcp_omni_connect/issues
Author-email: Abiola Adeshina <abiolaadedayo1993@gmail.com>
License: MIT
License-File: LICENSE
Keywords: agent,ai,automation,git,llm,mcp
Classifier: Development Status :: 4 - Beta
Classifier: Intended Audience :: Developers
Classifier: License :: OSI Approved :: MIT License
Classifier: Programming Language :: Python :: 3
Classifier: Programming Language :: Python :: 3.10
Classifier: Programming Language :: Python :: 3.11
Classifier: Programming Language :: Python :: 3.12
Classifier: Programming Language :: Python :: 3.13
Requires-Python: >=3.10
Requires-Dist: anyio>=4.2.0
Requires-Dist: apscheduler>=3.11.0
Requires-Dist: chromadb>=1.0.15
Requires-Dist: colorama>=0.4.6
Requires-Dist: colorlog>=6.9.0
Requires-Dist: einops>=0.8.1
Requires-Dist: fastapi-sso>=0.18.0
Requires-Dist: fastapi>=0.115.12
Requires-Dist: httpx-sse>=0.4.0
Requires-Dist: httpx>=0.26.0
Requires-Dist: litellm>=1.75.2
Requires-Dist: mcp[cli]>=1.9.1
Requires-Dist: nomic>=3.5.3
Requires-Dist: opik>=1.8.19
Requires-Dist: psutil>=7.0.0
Requires-Dist: psycopg2-binary>=2.9.10
Requires-Dist: pydantic[email]>=2.6.0
Requires-Dist: pymupdf>=1.26.3
Requires-Dist: python-decouple>=3.8
Requires-Dist: python-dotenv>=1.0.1
Requires-Dist: python-multipart>=0.0.20
Requires-Dist: qdrant-client>=1.15.0
Requires-Dist: redis>=5.2.1
Requires-Dist: rich>=13.9.4
Requires-Dist: sentence-transformers>=5.0.0
Requires-Dist: sqlalchemy>=2.0.0
Requires-Dist: tzlocal>=5.2
Requires-Dist: websockets>=15.0.1
